LICENSE
MANIFEST.in
README.rst
setup.py
bee_django_crm/__init__.py
bee_django_crm/admin.py
bee_django_crm/apps.py
bee_django_crm/decorators.py
bee_django_crm/exports.py
bee_django_crm/forms.py
bee_django_crm/models.py
bee_django_crm/signals.py
bee_django_crm/tests.py
bee_django_crm/urls.py
bee_django_crm/utils.py
bee_django_crm/validators.py
bee_django_crm/views.py
bee_django_crm/wxapp.py
bee_django_crm/wxapp_urls.py
bee_django_crm/management/.DS_Store
bee_django_crm/management/__init__.py
bee_django_crm/management/__init__.pyc
bee_django_crm/management/commands/__init__.py
bee_django_crm/management/commands/__init__.pyc
bee_django_crm/management/commands/init_city_db.py
bee_django_crm/management/commands/init_city_db.pyc
bee_django_crm/migrations/0001_initial.py
bee_django_crm/migrations/0001_initial.pyc
bee_django_crm/migrations/0002_auto_20180517_1758.py
bee_django_crm/migrations/0002_auto_20180517_1758.pyc
bee_django_crm/migrations/0002_qrcode.pyc
bee_django_crm/migrations/0003_auto_20180608_1917.py
bee_django_crm/migrations/0003_auto_20180608_1917.pyc
bee_django_crm/migrations/0003_delete_qrcode.pyc
bee_django_crm/migrations/0004_auto_20180622_1603.py
bee_django_crm/migrations/0004_auto_20180622_1603.pyc
bee_django_crm/migrations/0005_auto_20180708_1503.py
bee_django_crm/migrations/0005_auto_20180708_1503.pyc
bee_django_crm/migrations/0006_auto_20180822_1736.py
bee_django_crm/migrations/0006_auto_20180822_1736.pyc
bee_django_crm/migrations/0007_auto_20180823_1533.py
bee_django_crm/migrations/0007_auto_20180823_1533.pyc
bee_django_crm/migrations/0008_preuser_pay_status.py
bee_django_crm/migrations/0008_preuser_pay_status.pyc
bee_django_crm/migrations/0009_applicationquestion_is_required.py
bee_django_crm/migrations/0009_applicationquestion_is_required.pyc
bee_django_crm/migrations/0010_auto_20180823_1851.py
bee_django_crm/migrations/0010_auto_20180823_1851.pyc
bee_django_crm/migrations/0011_auto_20180828_1556.py
bee_django_crm_auth.egg-info/PKG-INFO
bee_django_crm_auth.egg-info/SOURCES.txt
bee_django_crm_auth.egg-info/dependency_links.txt
bee_django_crm_auth.egg-info/requires.txt
bee_django_crm_auth.egg-info/top_level.txt